linkloom/__init__.py
linkloom/cli.py
linkloom-0.0.2.dist-info/licenses/LICENSE
linkloom-0.0.2.dist-info/WHEEL
linkloom-0.0.2.dist-info/entry_points.txt
linkloom-0.0.2.dist-info/METADATA
linkloom-0.0.2.dist-info/RECORD
