Metadata-Version: 2.4
Name: linkloom
Version: 0.0.2
Summary: LinkLoom is a command-line bookmark manager that allows you to save and find your bookmarks using natural language queries. Instead of searching by tags or keywords, you can search by meaning.
Keywords: Bookmark,Organize,Productivity,Fast,Vector Search
Author: Neirzhei
Author-email: Neirzhei <neirzhei@gmail.com>
License-Expression: MIT
License-File: LICENSE
Classifier: Programming Language :: Python :: 3
Classifier: Operating System :: OS Independent
Classifier: Intended Audience :: Developers
Requires-Dist: typer==0.16.0
Requires-Dist: torch
Requires-Dist: sentence-transformers==5.1.0
Requires-Dist: trafilatura
Requires-Dist: httpx
Requires-Dist: chromadb==1.0.20
Requires-Python: >=3.9
Project-URL: Issues, https://github.com/neirzhei/LinkLoom/issues
Project-URL: Repository, https://github.com/neirzhei/LinkLoom
